ragas_once/__init__.py
ragas_once/cli.py
ragas_once/wrapper.py
raga_once-0.0.3.dist-info/LICENSE
raga_once-0.0.3.dist-info/METADATA
raga_once-0.0.3.dist-info/WHEEL
raga_once-0.0.3.dist-info/top_level.txt
raga_once-0.0.3.dist-info/RECORD
