Metadata-Version: 2.1
Name: raga-once
Version: 0.0.3
Summary: A one-step Ragas cli tool to evaluate RAG apps
Home-page: https://github.com/kubeagi/arcadia/evaluation/ragacli_pyproject
Author: Kielo
Author-email: Kielo <lanture1064@gmail.com>
Classifier: Programming Language :: Python :: 3
Classifier: License :: OSI Approved :: MIT License
Classifier: Operating System :: OS Independent
Requires-Python: >=3.8
License-File: LICENSE
